tiller_sheets_export/__init__.py
tiller_sheets_export/cli.py
tiller_sheets_export/dataset.py
tiller_sheets_export/pipeline.py
tiller_sheets_export/py.typed
tiller_sheets_export/sheets.py
tiller_sheets_export-0.1.2.dist-info/WHEEL
tiller_sheets_export-0.1.2.dist-info/entry_points.txt
tiller_sheets_export-0.1.2.dist-info/METADATA
tiller_sheets_export-0.1.2.dist-info/RECORD
