Metadata-Version: 2.3
Name: tiller-sheets-export
Version: 0.1.2
Summary: Unofficial tool to fetch Tiller financial data from Google Sheets as Arrow, DuckDB, or Parquet
Author: Fernando Grunevald
Author-email: Fernando Grunevald <fernandogrd@gmail.com>
License: MIT
Classifier: Development Status :: 4 - Beta
Classifier: Intended Audience :: Developers
Classifier: License :: OSI Approved :: MIT License
Classifier: Programming Language :: Python :: 3
Classifier: Programming Language :: Python :: 3.10
Classifier: Programming Language :: Python :: 3.11
Classifier: Programming Language :: Python :: 3.12
Classifier: Programming Language :: Python :: 3.13
Classifier: Topic :: Office/Business :: Financial
Classifier: Topic :: Office/Business :: Financial :: Spreadsheet
Classifier: Topic :: Utilities
Requires-Dist: click>=8.0
Requires-Dist: duckdb>=1.4.0
Requires-Dist: google-auth[urllib3]>=2.15.0
Requires-Dist: pyarrow>=14.0.0
Requires-Dist: urllib3>=2.0.0
Requires-Python: >=3.10
Project-URL: Repository, https://github.com/fernandogrd/tiller-sheets-export
Project-URL: Issues, https://github.com/fernandogrd/tiller-sheets-export/issues
